[
  {
    "name": "UNINOVA",
    "ref": null,
    "center": [
      -9.20412368,
      38.66017108
    ]
  },
  {
    "name": "Building VI",
    "ref": null,
    "center": [
      -9.203037477777778,
      38.66062547777778
    ]
  },
  {
    "name": "CENIMAT",
    "ref": null,
    "center": [
      -9.20345704,
      38.65945034
    ]
  },
  {
    "name": "CEMOP",
    "ref": null,
    "center": [
      -9.20369306,
      38.65980382
    ]
  },
  {
    "name": "Building X",
    "ref": null,
    "center": [
      -9.204861185714288,
      38.660560471428575
    ]
  },
  {
    "name": "Biblioteca FCT/UNL",
    "ref": null,
    "center": [
      -9.205231996428575,
      38.66267265357143
    ]
  },
  {
    "name": "Building XI",
    "ref": null,
    "center": [
      -9.206507241666667,
      38.662954199999994
    ]
  },
  {
    "name": "Unknown",
    "ref": null,
    "center": [
      -9.20651928,
      38.66282316
    ]
  },
  {
    "name": "Building V: Caixa Geral de Depósitos Auditorium",
    "ref": null,
    "center": [
      -9.206870922222222,
      38.66334064444444
    ]
  },
  {
    "name": "Building IX: Department of Earth Sciences",
    "ref": null,
    "center": [
      -9.20712042,
      38.66061884
    ]
  },
  {
    "name": "Building IX: Department of Civil Engineering",
    "ref": null,
    "center": [
      -9.207107340000004,
      38.65992619499999
    ]
  },
  {
    "name": "Building VIII",
    "ref": null,
    "center": [
      -9.206628861904761,
      38.66012034285715
    ]
  },
  {
    "name": "Centro de Educação Pré-Escolar dos Serviços de Ação Social da Universidade Nova de Lisboa",
    "ref": "804120",
    "center": [
      -9.204195511111111,
      38.6620453
    ]
  },
  {
    "name": "Unknown",
    "ref": null,
    "center": [
      -9.20434426,
      38.66268290000001
    ]
  },
  {
    "name": "Building VII",
    "ref": null,
    "center": [
      -9.205843935,
      38.6604363
    ]
  },
  {
    "name": "Building I",
    "ref": null,
    "center": [
      -9.205753437037036,
      38.661427840740735
    ]
  },
  {
    "name": "Canteen",
    "ref": null,
    "center": [
      -9.204890564,
      38.661487564
    ]
  },
  {
    "name": "Unknown",
    "ref": null,
    "center": [
      -9.203680819999999,
      38.678239379999994
    ]
  },
  {
    "name": "Unknown",
    "ref": null,
    "center": [
      -9.202972171428572,
      38.67842317142858
    ]
  },
  {
    "name": "Unknown",
    "ref": null,
    "center": [
      -9.204616042857143,
      38.6780525
    ]
  },
  {
    "name": "Unknown",
    "ref": null,
    "center": [
      -9.2037303,
      38.6634565
    ]
  },
  {
    "name": "Unknown",
    "ref": null,
    "center": [
      -9.202879471428572,
      38.66361794285714
    ]
  },
  {
    "name": "Unknown",
    "ref": null,
    "center": [
      -9.20350218,
      38.66325064
    ]
  },
  {
    "name": "Unknown",
    "ref": null,
    "center": [
      -9.202846560000001,
      38.66385042
    ]
  },
  {
    "name": "Unknown",
    "ref": null,
    "center": [
      -9.203277883333334,
      38.6633067
    ]
  },
  {
    "name": "Unknown",
    "ref": null,
    "center": [
      -9.2028744,
      38.663035840000006
    ]
  },
  {
    "name": "baticonta",
    "ref": null,
    "center": [
      -9.2029582,
      38.66312508
    ]
  },
  {
    "name": "Unknown",
    "ref": null,
    "center": [
      -9.203005083333332,
      38.663783
    ]
  },
  {
    "name": "Unknown",
    "ref": null,
    "center": [
      -9.2029465,
      38.663205100000006
    ]
  },
  {
    "name": "Unknown",
    "ref": null,
    "center": [
      -9.203635385714287,
      38.66314381428572
    ]
  },
  {
    "name": "Unknown",
    "ref": null,
    "center": [
      -9.203574816666666,
      38.66308961666667
    ]
  },
  {
    "name": "Unknown",
    "ref": null,
    "center": [
      -9.2062238,
      38.670894739999994
    ]
  },
  {
    "name": "Unknown",
    "ref": null,
    "center": [
      -9.20621006,
      38.67011788
    ]
  },
  {
    "name": "Unknown",
    "ref": null,
    "center": [
      -9.205805340000001,
      38.66915066
    ]
  },
  {
    "name": "Unknown",
    "ref": null,
    "center": [
      -9.20555826,
      38.66884046
    ]
  },
  {
    "name": "Unknown",
    "ref": null,
    "center": [
      -9.205286942857143,
      38.66825337142858
    ]
  },
  {
    "name": "Unknown",
    "ref": null,
    "center": [
      -9.205933859999998,
      38.6695232
    ]
  },
  {
    "name": "Unknown",
    "ref": null,
    "center": [
      -9.206916216666668,
      38.67688771666666
    ]
  },
  {
    "name": "Unknown",
    "ref": null,
    "center": [
      -9.205627428571429,
      38.66934955714286
    ]
  },
  {
    "name": "Unknown",
    "ref": null,
    "center": [
      -9.206900383333334,
      38.67668883333333
    ]
  },
  {
    "name": "Unknown",
    "ref": null,
    "center": [
      -9.20693296,
      38.67678808
    ]
  },
  {
    "name": "Unknown",
    "ref": null,
    "center": [
      -9.2060157,
      38.6707025
    ]
  },
  {
    "name": "Unknown",
    "ref": null,
    "center": [
      -9.206431328571428,
      38.671049257142855
    ]
  },
  {
    "name": "Unknown",
    "ref": null,
    "center": [
      -9.20689054,
      38.67582806
    ]
  },
  {
    "name": "Unknown",
    "ref": null,
    "center": [
      -9.20652472,
      38.6699925
    ]
  },
  {
    "name": "Unknown",
    "ref": null,
    "center": [
      -9.20607016,
      38.66965354
    ]
  },
  {
    "name": "Unknown",
    "ref": null,
    "center": [
      -9.205955633333334,
      38.669577216666674
    ]
  },
  {
    "name": "Unknown",
    "ref": null,
    "center": [
      -9.206890266666667,
      38.67632143333334
    ]
  },
  {
    "name": "Unknown",
    "ref": null,
    "center": [
      -9.20611832,
      38.669730040000005
    ]
  },
  {
    "name": "Unknown",
    "ref": null,
    "center": [
      -9.20598666,
      38.66915668
    ]
  },
  {
    "name": "Unknown",
    "ref": null,
    "center": [
      -9.2069265,
      38.675698940000004
    ]
  },
  {
    "name": "Unknown",
    "ref": null,
    "center": [
      -9.20571996,
      38.668638400000006
    ]
  },
  {
    "name": "Unknown",
    "ref": null,
    "center": [
      -9.206885828571428,
      38.6770235
    ]
  },
  {
    "name": "Unknown",
    "ref": null,
    "center": [
      -9.20616375,
      38.66980738333333
    ]
  },
  {
    "name": "Unknown",
    "ref": null,
    "center": [
      -9.206684114285716,
      38.67643284285714
    ]
  },
  {
    "name": "Unknown",
    "ref": null,
    "center": [
      -9.20650455,
      38.67754873333333
    ]
  },
  {
    "name": "Unknown",
    "ref": null,
    "center": [
      -9.20687992,
      38.67596492
    ]
  },
  {
    "name": "Unknown",
    "ref": null,
    "center": [
      -9.206884380000002,
      38.676045959999996
    ]
  },
  {
    "name": "Unknown",
    "ref": null,
    "center": [
      -9.205510233333333,
      38.66842598333333
    ]
  },
  {
    "name": "Unknown",
    "ref": null,
    "center": [
      -9.207098633333333,
      38.67437638333334
    ]
  },
  {
    "name": "Unknown",
    "ref": null,
    "center": [
      -9.20695872,
      38.675487079999996
    ]
  },
  {
    "name": "Unknown",
    "ref": null,
    "center": [
      -9.20695286,
      38.6753982
    ]
  },
  {
    "name": "Unknown",
    "ref": null,
    "center": [
      -9.206718,
      38.677281566666665
    ]
  },
  {
    "name": "Unknown",
    "ref": null,
    "center": [
      -9.20540364,
      38.66835236
    ]
  },
  {
    "name": "Unknown",
    "ref": null,
    "center": [
      -9.206875550000001,
      38.676136183333334
    ]
  },
  {
    "name": "Unknown",
    "ref": null,
    "center": [
      -9.20700768,
      38.67709291999999
    ]
  },
  {
    "name": "Unknown",
    "ref": null,
    "center": [
      -9.207032700000001,
      38.67489915714286
    ]
  },
  {
    "name": "Unknown",
    "ref": null,
    "center": [
      -9.206969079999999,
      38.67556654
    ]
  },
  {
    "name": "Unknown",
    "ref": null,
    "center": [
      -9.20629348,
      38.671139
    ]
  },
  {
    "name": "Café Charcutaria Onofre",
    "ref": null,
    "center": [
      -9.20591172,
      38.669384019999995
    ]
  },
  {
    "name": "Unknown",
    "ref": null,
    "center": [
      -9.206195866666667,
      38.670775733333336
    ]
  },
  {
    "name": "Unknown",
    "ref": null,
    "center": [
      -9.206575171428572,
      38.67739261428572
    ]
  },
  {
    "name": "Unknown",
    "ref": null,
    "center": [
      -9.205904100000001,
      38.66946024
    ]
  },
  {
    "name": "Unknown",
    "ref": null,
    "center": [
      -9.20626816,
      38.66990933999999
    ]
  },
  {
    "name": "Unknown",
    "ref": null,
    "center": [
      -9.206231016666669,
      38.670651516666666
    ]
  },
  {
    "name": "Unknown",
    "ref": null,
    "center": [
      -9.205865055555556,
      38.668844577777776
    ]
  },
  {
    "name": "Unknown",
    "ref": null,
    "center": [
      -9.20576202,
      38.668718340000005
    ]
  },
  {
    "name": "Unknown",
    "ref": null,
    "center": [
      -9.206030940000002,
      38.66901386
    ]
  },
  {
    "name": "Unknown",
    "ref": null,
    "center": [
      -9.20691456,
      38.676205980000006
    ]
  },
  {
    "name": "Unknown",
    "ref": null,
    "center": [
      -9.2059715,
      38.67051008
    ]
  },
  {
    "name": "Unknown",
    "ref": null,
    "center": [
      -9.206929030000001,
      38.6771641
    ]
  },
  {
    "name": "Oficina da Cooperativa dos Catraeiros",
    "ref": null,
    "center": [
      -9.2068388375,
      38.6764874125
    ]
  },
  {
    "name": "Unknown",
    "ref": null,
    "center": [
      -9.20675344,
      38.6765608
    ]
  },
  {
    "name": "Unknown",
    "ref": null,
    "center": [
      -9.2060286,
      38.6705962
    ]
  },
  {
    "name": "Unknown",
    "ref": null,
    "center": [
      -9.205595928571428,
      38.6690056
    ]
  },
  {
    "name": "Quinta da Azenha",
    "ref": null,
    "center": [
      -9.206597933333333,
      38.671143083333334
    ]
  },
  {
    "name": "Estação Fluvial de Porto Brandão",
    "ref": null,
    "center": [
      -9.20666285,
      38.67788999
    ]
  },
  {
    "name": "Unknown",
    "ref": null,
    "center": [
      -9.2058058,
      38.66973282
    ]
  },
  {
    "name": "Unknown",
    "ref": null,
    "center": [
      -9.20562438,
      38.66959316
    ]
  },
  {
    "name": "Unknown",
    "ref": null,
    "center": [
      -9.205600100000002,
      38.66972314
    ]
  },
  {
    "name": "Unknown",
    "ref": null,
    "center": [
      -9.205672380000001,
      38.66951676
    ]
  },
  {
    "name": "Unknown",
    "ref": null,
    "center": [
      -9.205114566666667,
      38.66817901111111
    ]
  },
  {
    "name": "Unknown",
    "ref": null,
    "center": [
      -9.2054899,
      38.669241899999996
    ]
  },
  {
    "name": "Unknown",
    "ref": null,
    "center": [
      -9.204368559999999,
      38.665520019999995
    ]
  },
  {
    "name": "Unknown",
    "ref": null,
    "center": [
      -9.204500544444445,
      38.6684023
    ]
  },
  {
    "name": "Unknown",
    "ref": null,
    "center": [
      -9.20477726,
      38.66819798
    ]
  },
  {
    "name": "Unknown",
    "ref": null,
    "center": [
      -9.205072759999998,
      38.66847332
    ]
  },
  {
    "name": "Unknown",
    "ref": null,
    "center": [
      -9.20548282,
      38.66693227999999
    ]
  },
  {
    "name": "Unknown",
    "ref": null,
    "center": [
      -9.20479722,
      38.66801506
    ]
  },
  {
    "name": "Unknown",
    "ref": null,
    "center": [
      -9.20493486,
      38.6677028
    ]
  },
  {
    "name": "Unknown",
    "ref": null,
    "center": [
      -9.2047828,
      38.6685227
    ]
  },
  {
    "name": "Unknown",
    "ref": null,
    "center": [
      -9.204669616666665,
      38.668424433333335
    ]
  },
  {
    "name": "Unknown",
    "ref": null,
    "center": [
      -9.20505828,
      38.668715920000004
    ]
  },
  {
    "name": "Unknown",
    "ref": null,
    "center": [
      -9.204977383333334,
      38.66815173333334
    ]
  },
  {
    "name": "Unknown",
    "ref": null,
    "center": [
      -9.20474552,
      38.667857299999994
    ]
  },
  {
    "name": "Unknown",
    "ref": null,
    "center": [
      -9.20478648,
      38.66794652
    ]
  },
  {
    "name": "Unknown",
    "ref": null,
    "center": [
      -9.20426012,
      38.66610748
    ]
  },
  {
    "name": "Unknown",
    "ref": null,
    "center": [
      -9.20332882,
      38.66815942
    ]
  },
  {
    "name": "Unknown",
    "ref": null,
    "center": [
      -9.204871999999998,
      38.66780456
    ]
  },
  {
    "name": "Unknown",
    "ref": null,
    "center": [
      -9.20468172,
      38.66856914
    ]
  },
  {
    "name": "Unknown",
    "ref": null,
    "center": [
      -9.203611909090908,
      38.66785005454546
    ]
  },
  {
    "name": "Unknown",
    "ref": null,
    "center": [
      -9.204710299999999,
      38.66568206000001
    ]
  },
  {
    "name": "Unknown",
    "ref": null,
    "center": [
      -9.20563512,
      38.667405759999994
    ]
  },
  {
    "name": "Unknown",
    "ref": null,
    "center": [
      -9.20540136,
      38.66672922
    ]
  },
  {
    "name": "Unknown",
    "ref": null,
    "center": [
      -9.20460406,
      38.6685107
    ]
  },
  {
    "name": "Unknown",
    "ref": null,
    "center": [
      -9.20494802,
      38.667238340000004
    ]
  },
  {
    "name": "Unknown",
    "ref": null,
    "center": [
      -9.204869216666667,
      38.668199
    ]
  },
  {
    "name": "Unknown",
    "ref": null,
    "center": [
      -9.20526674,
      38.66704416
    ]
  },
  {
    "name": "Unknown",
    "ref": null,
    "center": [
      -9.20523162,
      38.6662607
    ]
  },
  {
    "name": "Unknown",
    "ref": null,
    "center": [
      -9.20520042,
      38.6661188
    ]
  },
  {
    "name": "Unknown",
    "ref": null,
    "center": [
      -9.2047136,
      38.66794068
    ]
  },
  {
    "name": "Unknown",
    "ref": null,
    "center": [
      -9.20568898,
      38.66758808
    ]
  },
  {
    "name": "Unknown",
    "ref": null,
    "center": [
      -9.204388,
      38.666127744444445
    ]
  },
  {
    "name": "Unknown",
    "ref": null,
    "center": [
      -9.204939419999999,
      38.66553166
    ]
  },
  {
    "name": "Unknown",
    "ref": null,
    "center": [
      -9.204535233333335,
      38.66855887777778
    ]
  },
  {
    "name": "Unknown",
    "ref": null,
    "center": [
      -9.204803216666667,
      38.66831783333333
    ]
  },
  {
    "name": "Unknown",
    "ref": null,
    "center": [
      -9.20517862857143,
      38.6685289
    ]
  },
  {
    "name": "Unknown",
    "ref": null,
    "center": [
      -9.2049626,
      38.665776320000006
    ]
  },
  {
    "name": "Unknown",
    "ref": null,
    "center": [
      -9.204906679999999,
      38.66646558
    ]
  },
  {
    "name": "Unknown",
    "ref": null,
    "center": [
      -9.204795585714285,
      38.66806747142858
    ]
  },
  {
    "name": "Unknown",
    "ref": null,
    "center": [
      -9.205364144444445,
      38.66770666666667
    ]
  },
  {
    "name": "Unknown",
    "ref": null,
    "center": [
      -9.2051327,
      38.665945900000004
    ]
  },
  {
    "name": "Unknown",
    "ref": null,
    "center": [
      -9.205558385714285,
      38.66713061428572
    ]
  },
  {
    "name": "Unknown",
    "ref": null,
    "center": [
      -9.2049199,
      38.66799805
    ]
  },
  {
    "name": "Unknown",
    "ref": null,
    "center": [
      -9.20444228,
      38.6657788
    ]
  },
  {
    "name": "Unknown",
    "ref": null,
    "center": [
      -9.204702716666667,
      38.668091800000006
    ]
  },
  {
    "name": "Unknown",
    "ref": null,
    "center": [
      -9.205002200000001,
      38.66674062
    ]
  },
  {
    "name": "Unknown",
    "ref": null,
    "center": [
      -9.204957400000001,
      38.66821508
    ]
  },
  {
    "name": "Unknown",
    "ref": null,
    "center": [
      -9.2042287,
      38.668063676923076
    ]
  },
  {
    "name": "Unknown",
    "ref": null,
    "center": [
      -9.20427876,
      38.66621894
    ]
  },
  {
    "name": "Unknown",
    "ref": null,
    "center": [
      -9.204817071428574,
      38.667861200000004
    ]
  },
  {
    "name": "Unknown",
    "ref": null,
    "center": [
      -9.204969219999999,
      38.668049620000005
    ]
  },
  {
    "name": "Unknown",
    "ref": null,
    "center": [
      -9.205350939999999,
      38.66655704
    ]
  },
  {
    "name": "Unknown",
    "ref": null,
    "center": [
      -9.203830257142856,
      38.66822318571428
    ]
  },
  {
    "name": "Unknown",
    "ref": null,
    "center": [
      -9.2052828,
      38.666404060000005
    ]
  },
  {
    "name": "Unknown",
    "ref": null,
    "center": [
      -9.20492548,
      38.66793896
    ]
  },
  {
    "name": "Unknown",
    "ref": null,
    "center": [
      -9.205024742857145,
      38.66834371428571
    ]
  },
  {
    "name": "Unknown",
    "ref": null,
    "center": [
      -9.20496475,
      38.6678688
    ]
  },
  {
    "name": "Unknown",
    "ref": null,
    "center": [
      -9.20298416,
      38.66701574
    ]
  },
  {
    "name": "Unknown",
    "ref": null,
    "center": [
      -9.203805814285715,
      38.6669677
    ]
  },
  {
    "name": "Unknown",
    "ref": null,
    "center": [
      -9.203962683333332,
      38.667037949999994
    ]
  },
  {
    "name": "Unknown",
    "ref": null,
    "center": [
      -9.204408275,
      38.666665800000004
    ]
  },
  {
    "name": "Unknown",
    "ref": null,
    "center": [
      -9.205153662499999,
      38.66800235
    ]
  },
  {
    "name": "Unknown",
    "ref": null,
    "center": [
      -9.204889500000002,
      38.66705606
    ]
  },
  {
    "name": "Unknown",
    "ref": null,
    "center": [
      -9.203593,
      38.66687686
    ]
  },
  {
    "name": "Unknown",
    "ref": null,
    "center": [
      -9.20481558,
      38.666888799999995
    ]
  },
  {
    "name": "Unknown",
    "ref": null,
    "center": [
      -9.20305262,
      38.66775642
    ]
  },
  {
    "name": "Unknown",
    "ref": null,
    "center": [
      -9.20295556,
      38.6669111
    ]
  },
  {
    "name": "Unknown",
    "ref": null,
    "center": [
      -9.2032469,
      38.667876920000005
    ]
  },
  {
    "name": "Unknown",
    "ref": null,
    "center": [
      -9.204549416666667,
      38.66655335
    ]
  },
  {
    "name": "Unknown",
    "ref": null,
    "center": [
      -9.20480558,
      38.66718858
    ]
  },
  {
    "name": "Unknown",
    "ref": null,
    "center": [
      -9.204616999999999,
      38.66767018
    ]
  },
  {
    "name": "Unknown",
    "ref": null,
    "center": [
      -9.2030801,
      38.667236
    ]
  },
  {
    "name": "Unknown",
    "ref": null,
    "center": [
      -9.204757759999998,
      38.66701020000001
    ]
  },
  {
    "name": "Unknown",
    "ref": null,
    "center": [
      -9.20485762,
      38.66740912
    ]
  },
  {
    "name": "Unknown",
    "ref": null,
    "center": [
      -9.20483342,
      38.667272620000006
    ]
  },
  {
    "name": "Unknown",
    "ref": null,
    "center": [
      -9.205063233333332,
      38.66771713333333
    ]
  },
  {
    "name": "Unknown",
    "ref": null,
    "center": [
      -9.205076933333332,
      38.66788461666666
    ]
  },
  {
    "name": "Unknown",
    "ref": null,
    "center": [
      -9.20316875,
      38.66779891
    ]
  },
  {
    "name": "Unknown",
    "ref": null,
    "center": [
      -9.20381432,
      38.66714574
    ]
  },
  {
    "name": "Unknown",
    "ref": null,
    "center": [
      -9.204791914285712,
      38.66735155714286
    ]
  },
  {
    "name": "Unknown",
    "ref": null,
    "center": [
      -9.20492716,
      38.66761024
    ]
  },
  {
    "name": "Unknown",
    "ref": null,
    "center": [
      -9.20489335,
      38.66755653333333
    ]
  },
  {
    "name": "Unknown",
    "ref": null,
    "center": [
      -9.2048791,
      38.66748522
    ]
  },
  {
    "name": "Unknown",
    "ref": null,
    "center": [
      -9.203726442857143,
      38.666807428571424
    ]
  },
  {
    "name": "Unknown",
    "ref": null,
    "center": [
      -9.20448506,
      38.66660284
    ]
  },
  {
    "name": "Unknown",
    "ref": null,
    "center": [
      -9.203345500000001,
      38.66779765
    ]
  },
  {
    "name": "Unknown",
    "ref": null,
    "center": [
      -9.20478056,
      38.6671018
    ]
  },
  {
    "name": "My Spot",
    "ref": null,
    "center": [
      -9.20560962,
      38.66055042000001
    ]
  },
  {
    "name": "Capela de São Tomás de Aquino",
    "ref": null,
    "center": [
      -9.20470402,
      38.66502792
    ]
  },
  {
    "name": "Lidl",
    "ref": "582",
    "center": [
      -9.2039449,
      38.65905402
    ]
  },
  {
    "name": "Unknown",
    "ref": null,
    "center": [
      -9.203259039999999,
      38.66029583
    ]
  },
  {
    "name": "Unknown",
    "ref": null,
    "center": [
      -9.20352866,
      38.66106878000001
    ]
  },
  {
    "name": "Unknown",
    "ref": null,
    "center": [
      -9.20338536,
      38.66021908
    ]
  },
  {
    "name": "Unknown",
    "ref": null,
    "center": [
      -9.206397916666665,
      38.661888166666664
    ]
  },
  {
    "name": "Unknown",
    "ref": null,
    "center": [
      -9.20389198,
      38.663257540000004
    ]
  },
  {
    "name": "Unknown",
    "ref": null,
    "center": [
      -9.20377552,
      38.66317742
    ]
  },
  {
    "name": "Unknown",
    "ref": null,
    "center": [
      -9.20548926,
      38.6645008
    ]
  },
  {
    "name": "Unknown",
    "ref": null,
    "center": [
      -9.205324959999999,
      38.66437168
    ]
  },
  {
    "name": "Unknown",
    "ref": null,
    "center": [
      -9.205135844444445,
      38.66435292222223
    ]
  },
  {
    "name": "Unknown",
    "ref": null,
    "center": [
      -9.205332799999999,
      38.664476779999994
    ]
  },
  {
    "name": "Unknown",
    "ref": null,
    "center": [
      -9.205206919999998,
      38.66387486
    ]
  },
  {
    "name": "Unknown",
    "ref": null,
    "center": [
      -9.20530986,
      38.66390972
    ]
  },
  {
    "name": "Unknown",
    "ref": null,
    "center": [
      -9.2054541,
      38.66395316
    ]
  },
  {
    "name": "Unknown",
    "ref": null,
    "center": [
      -9.20548166,
      38.664064180000004
    ]
  },
  {
    "name": "Unknown",
    "ref": null,
    "center": [
      -9.20548106,
      38.664169560000005
    ]
  },
  {
    "name": "Unknown",
    "ref": null,
    "center": [
      -9.2054814,
      38.664239380000005
    ]
  },
  {
    "name": "Unknown",
    "ref": null,
    "center": [
      -9.206130700000001,
      38.66401091111111
    ]
  },
  {
    "name": "Unknown",
    "ref": null,
    "center": [
      -9.206790314285714,
      38.66398244285714
    ]
  },
  {
    "name": "Unknown",
    "ref": null,
    "center": [
      -9.20680764,
      38.664144359999995
    ]
  },
  {
    "name": "Unknown",
    "ref": null,
    "center": [
      -9.206793516666666,
      38.6642883
    ]
  },
  {
    "name": "Unknown",
    "ref": null,
    "center": [
      -9.20699574,
      38.663945160000004
    ]
  },
  {
    "name": "Unknown",
    "ref": null,
    "center": [
      -9.206535766666667,
      38.66445233333334
    ]
  },
  {
    "name": "Unknown",
    "ref": null,
    "center": [
      -9.206416287500002,
      38.664401575
    ]
  },
  {
    "name": "Unknown",
    "ref": null,
    "center": [
      -9.206672483333334,
      38.663896949999994
    ]
  },
  {
    "name": "Unknown",
    "ref": null,
    "center": [
      -9.20664712,
      38.663973479999996
    ]
  },
  {
    "name": "Unknown",
    "ref": null,
    "center": [
      -9.206650020000001,
      38.664110959999995
    ]
  },
  {
    "name": "Unknown",
    "ref": null,
    "center": [
      -9.206656800000001,
      38.6642715
    ]
  },
  {
    "name": "Unknown",
    "ref": null,
    "center": [
      -9.206686325,
      38.6643948375
    ]
  },
  {
    "name": "Unknown",
    "ref": null,
    "center": [
      -9.206723760000001,
      38.664292579999994
    ]
  },
  {
    "name": "Unknown",
    "ref": null,
    "center": [
      -9.2053854,
      38.674882319999995
    ]
  },
  {
    "name": "Unknown",
    "ref": null,
    "center": [
      -9.20569098,
      38.6748654
    ]
  },
  {
    "name": "Unknown",
    "ref": null,
    "center": [
      -9.20581036,
      38.67478036
    ]
  },
  {
    "name": "Unknown",
    "ref": null,
    "center": [
      -9.20598866,
      38.67485036
    ]
  },
  {
    "name": "Unknown",
    "ref": null,
    "center": [
      -9.205860920000001,
      38.674989339999996
    ]
  },
  {
    "name": "Unknown",
    "ref": null,
    "center": [
      -9.20572964,
      38.67497906
    ]
  },
  {
    "name": "Unknown",
    "ref": null,
    "center": [
      -9.20562762,
      38.6749663
    ]
  },
  {
    "name": "Unknown",
    "ref": null,
    "center": [
      -9.206051842857141,
      38.675057971428565
    ]
  },
  {
    "name": "Unknown",
    "ref": null,
    "center": [
      -9.20595602857143,
      38.67504014285714
    ]
  },
  {
    "name": "Unknown",
    "ref": null,
    "center": [
      -9.20621244,
      38.67495794
    ]
  },
  {
    "name": "Unknown",
    "ref": null,
    "center": [
      -9.2065071,
      38.6751239
    ]
  },
  {
    "name": "Unknown",
    "ref": null,
    "center": [
      -9.20636882,
      38.67509414
    ]
  },
  {
    "name": "Unknown",
    "ref": null,
    "center": [
      -9.206291460000001,
      38.674870899999995
    ]
  },
  {
    "name": "Unknown",
    "ref": null,
    "center": [
      -9.20608294,
      38.674893239999996
    ]
  },
  {
    "name": "Unknown",
    "ref": null,
    "center": [
      -9.2063314,
      38.67496732
    ]
  },
  {
    "name": "Unknown",
    "ref": null,
    "center": [
      -9.206441940000001,
      38.67492772
    ]
  },
  {
    "name": "Unknown",
    "ref": null,
    "center": [
      -9.206516980000002,
      38.67488702
    ]
  },
  {
    "name": "Unknown",
    "ref": null,
    "center": [
      -9.206209379999999,
      38.67484454
    ]
  },
  {
    "name": "Unknown",
    "ref": null,
    "center": [
      -9.206235920000001,
      38.67472858
    ]
  },
  {
    "name": "Unknown",
    "ref": null,
    "center": [
      -9.206065599999999,
      38.67465734
    ]
  },
  {
    "name": "Unknown",
    "ref": null,
    "center": [
      -9.20596338,
      38.67464242
    ]
  },
  {
    "name": "Unknown",
    "ref": null,
    "center": [
      -9.20584826,
      38.67460538
    ]
  },
  {
    "name": "Unknown",
    "ref": null,
    "center": [
      -9.205777939999999,
      38.674892979999996
    ]
  },
  {
    "name": "Unknown",
    "ref": null,
    "center": [
      -9.20586104,
      38.67486106
    ]
  },
  {
    "name": "Unknown",
    "ref": null,
    "center": [
      -9.2059884,
      38.6749486
    ]
  },
  {
    "name": "Unknown",
    "ref": null,
    "center": [
      -9.206154485714285,
      38.67504364285714
    ]
  },
  {
    "name": "Unknown",
    "ref": null,
    "center": [
      -9.20636434,
      38.67488546
    ]
  },
  {
    "name": "Building II",
    "ref": null,
    "center": [
      -9.203595720000001,
      38.6609647
    ]
  },
  {
    "name": "Edifício II: Departamento de Informática",
    "ref": null,
    "center": [
      -9.20330508,
      38.660955619999996
    ]
  },
  {
    "name": "Hangar 1",
    "ref": null,
    "center": [
      -9.206935060000001,
      38.66169943999999
    ]
  },
  {
    "name": "Hangar 2",
    "ref": null,
    "center": [
      -9.20680668,
      38.661910899999995
    ]
  },
  {
    "name": "Hangar 3",
    "ref": null,
    "center": [
      -9.20662736,
      38.66209218
    ]
  },
  {
    "name": "Center of Excellence of the Environment Building",
    "ref": null,
    "center": [
      -9.20612386,
      38.66228906
    ]
  }
]